pihole_dashboard/__init__.py
pihole_dashboard/font/font.ttf
pihole_dashboard-1.0.3.data/scripts/pihole-dashboard-clean-screen
pihole_dashboard-1.0.3.data/scripts/pihole-dashboard-draw
pihole_dashboard-1.0.3.dist-info/LICENSE.txt
pihole_dashboard-1.0.3.dist-info/METADATA
pihole_dashboard-1.0.3.dist-info/WHEEL
pihole_dashboard-1.0.3.dist-info/top_level.txt
pihole_dashboard-1.0.3.dist-info/RECORD
