Metadata-Version: 2.1
Name: pihole-dashboard
Version: 1.0.3
Summary: Minimal dashboard for Pi-Hole that works with WaveShare's 2.13 inch HAT display
Home-page: https://github.com/santoru/pihole-dashboard
Author: santoru
Author-email: santoru@pm.me
License: UNKNOWN
Platform: UNKNOWN
Requires-Python: >=3.3.5
Requires-Dist: Pillow (>=8.2.0)
Requires-Dist: netifaces (>=0.10.9)
Requires-Dist: toml (>=0.10.2)
Requires-Dist: waveshare-epd
